ndx_point_cloud_table/__init__.py
ndx_point_cloud_table/point_cloud_table.py
ndx_point_cloud_table/spec/ndx-point-cloud-table.extensions.yaml
ndx_point_cloud_table/spec/ndx-point-cloud-table.namespace.yaml
tests/__init__.py
tests/test.py
ndx_point_cloud_table-0.1.0.dist-info/LICENSE
ndx_point_cloud_table-0.1.0.dist-info/METADATA
ndx_point_cloud_table-0.1.0.dist-info/WHEEL
ndx_point_cloud_table-0.1.0.dist-info/top_level.txt
ndx_point_cloud_table-0.1.0.dist-info/RECORD
